{
    "pages": [ //pages数组中第一项表示应用启动页，参考：https://uniapp.dcloud.io/collocation/pages
        {
            "path": "pages/index/index",
            "name": "index",
            "meta": {
                "auth": false,
                "keepScroll": true
            },
            "style": {
                "navigationBarTitleText": "首页",
                "navigationStyle": "custom",
                "navigationBarTextStyle": "white",
                "app-plus": {
                    "bounce": "none"
                }

            }
        },
        {
            "path": "pages/order/order",
            "name": "order",
            "meta": {
                "auth": false,
                "keepScroll": true
            },
            "style": {
                "navigationBarTitleText": "商品"
            }
        },
        {
            "path": "pages/goods_detail/goods_detail",
            "name": "goods_detail",
            "meta": {
                "auth": false,
                "keepScroll": true
            },
            "style": {
                "navigationStyle":"custom",
                "navigationBarTitleText": "商品详情"
            }
        },
        {
            "path": "pages/order_list/order_list",
            "name": "order_list",
            "meta": {
                "auth": false,
                "keepScroll": true
            },
            "style": {
                "navigationBarTitleText": "我的订单"
            }
        },
        {
            "path": "pages/user/user",
            "name": "user",
            "meta": {
                "auth": false,
                "keepScroll": true
            },
            "style": {
                "navigationBarTitleText": "个人中心",
                "navigationStyle": "custom"
            }
        },
        {
            "path": "pages/user/transfer_test",
            "name": "transfer_test",
            "meta": {
                "auth": true
            },
            "style": {
                "navigationBarTitleText": "商家转账测试"
            }
        },
        {
            "path": "pages/login/login",
            "meta": {
                "auth": false
            },
            "style": {
                "navigationBarTitleText": "登录"
            }
        },
        {
            "path": "pages/confirm_order/confirm_order",
            "meta": {
                "auth": true
            },
            "style": {
                "navigationBarTitleText": "确认订单"
            }
        },
        {
            "path": "pages/payment/payment",
            "meta": {
                "auth": true
            },
            "style": {
                "navigationBarTitleText": "订单支付"
            }
        },
        {
            "path": "pages/pay_result/pay_result",
            "meta": {
                "auth": true
            },
            "style": {
                "navigationBarTitleText": "支付结果"
            }
        },
        {
            "path": "pages/order_detail/order_detail",
            "meta": {
                "auth": true
            },
            "style": {
                "navigationBarTitleText": "订单详情"
            }
        },
        {
            "path": "pages/webview/webview",
            "meta": {
                "auth": false
            }
        },
		{
            "path": "pages/forget_pwd/forget_pwd",
            "meta": {
                "auth": false
            },
            "style": {
                "navigationBarTitleText": "忘记密码"
            }
        },
{
            "path": "pages/register/register",
		    "meta": {
		        "auth": false
		    },
		    "style": {
		        "navigationBarTitleText": "注册账号"
		    }
		},
        {
            "path": "pages/marketing_chat/marketing_chat",
            "meta": {
                "auth": false
            },
            "style": {
                "navigationBarTitleText": "在线咨询",
                "navigationStyle": "custom"
            }
        },
        {
            "path": "components/uview-ui/components/u-avatar-cropper/u-avatar-cropper",
            "style": {
                "navigationBarTitleText": "头像裁剪",
                "navigationBarBackgroundColor": "#000000"
            }
        }
    ],
    "subPackages": [{
        "root": "bundle",
        "pages": [{
                "path": "pages/order_details/order_details",
                "meta": {
                    "auth": true
                },
                "style": {
                    "navigationBarTitleText": "订单详情"
                }
            },
            {
                "path": "pages/server_explan/server_explan",
                "meta": {
                    "auth": false
                },
                "style": {
                    "navigationBarTitleText": "服务协议"
                }
            },
            {
                "path": "pages/change_mobile/change_mobile",
                "meta": {
                    "auth": false
                },
                "style": {
                    "navigationBarTitleText": "更换手机号"
                }
            },
            {
                "path": "pages/bind_mobile/bind_mobile",
                "meta": {
                    "auth": false
                },
                "style": {
                    "navigationBarTitleText": "绑定手机号"
                }
            },
            {
                "path": "pages/store_list/store_list",
                "meta": {
                    "auth": false
                },
                "style": {
                    "navigationBarTitleText": "门店列表"
                }
            },
            {
                "path": "pages/user_address/user_address",
                "meta": {
                    "auth": true
                },
                "style": {
                    "navigationBarTitleText": "收货地址"
                }
            },
            {
                "path": "pages/address_edit/address_edit",
                "meta": {
                    "auth": true
                },
                "style": {
                    "navigationBarTitleText": "添加地址"
                }
            },
            {
                "path": "pages/user_profile/user_profile",
                "meta": {
                    "auth": true
                },
                "style": {
                    "navigationBarTitleText": "个人设置"
                }
            },
            {
                "path": "pages/user_recharge/user_recharge",
                "meta": {
                    "auth": true
                },
                "style": {
                    "navigationBarTitleText": "充值"
                }
            },
            {
            	"path": "pages/balance_details/balance_details",
            	"meta": {
            		"auth": true
            	},
            	"style": {
            		"navigationBarTitleText": "余额明细"
            	}
            },
            {
            	"path": "pages/service/service",
            	"meta": {
            		"auth": true
            	},
            	"style": {
                    "navigationStyle": "custom",
            		"navigationBarTitleText": "联系客服"
            	}
            },
            {
            	"path": "pages/address_switch/address_switch",
            	"meta": {
            		"auth": true
            	},
            	"style": {
            		"navigationBarTitleText": "切换城市"
            	}
            },
            {
            	"path": "pages/user_coupon/user_coupon",
            	"meta": {
            		"auth": true
            	},
            	"style": {
            		"navigationBarTitleText": "我的优惠券"
            	}
            },
            {
            	"path": "pages/file/file",
            	"style": {
            		"navigationBarTitleText": "食品安全档案"
            	}
            },
            {
            	"path": "pages/store_notice_detail/store_notice_detail",
            	"style": {
            		"navigationBarTitleText": "公告详情"
            	}
            }
        ]
    }],
    "tabBar": {
        "color": "#666",
        "selectedColor": "#67b849",
        "borderStyle": "black",
        "list": [{
                "pagePath": "pages/index/index",
                "iconPath": "/static/images/tab_home.png",
                "selectedIconPath": "/static/images/tab_home_s.png",
                "text": "首页"
            },
            {
                "pagePath": "pages/order/order",
                "iconPath": "/static/images/tab_shop.png",
                "selectedIconPath": "/static/images/tab_shop_s.png",
                "text": "点单"
            },
            {
                "pagePath": "pages/order_list/order_list",
                "iconPath": "/static/images/tab_order.png",
                "selectedIconPath": "/static/images/tab_order_s.png",
                "text": "订单"
            },
            {
                "pagePath": "pages/user/user",
                "iconPath": "/static/images/tab_user.png",
                "selectedIconPath": "/static/images/tab_user_s.png",
                "text": "我的"
            }
        ]
    },
    "globalStyle": {
        "navigationBarTextStyle": "black",
        "navigationBarTitleText": "LikeMall",
        "navigationBarBackgroundColor": "#FFFFFF",
        "backgroundColor": "#F8F8F8",
        "h5": {
            "navigationStyle": "custom"
        }

    },
    "easycom": {
        "autoscan": true,
        "custom": {
            "^u-(.*)": "@/components/uview-ui/components/u-$1/u-$1.vue"
        }
    }
}
